extmaillogin/__init__.py
extmaillogin/auth_backends.py
extmaillogin/middleware.py
extmaillogin-0.4.0.dist-info/LICENSE
extmaillogin-0.4.0.dist-info/METADATA
extmaillogin-0.4.0.dist-info/WHEEL
extmaillogin-0.4.0.dist-info/RECORD
